CHANGELOG.md
MANIFEST.in
setup.py
berth/__init__.py
berth/build.py
berth/cli.py
berth/config.py
berth/package.py
berth/utils.py
berth.egg-info/PKG-INFO
berth.egg-info/SOURCES.txt
berth.egg-info/dependency_links.txt
berth.egg-info/entry_points.txt
berth.egg-info/requires.txt
berth.egg-info/top_level.txt